{"apifoxProject":"1.0.0","$schema":{"app":"apifox","type":"project","version":"1.2.0"},"info":{"name":"HTTPBinGo","description":"本程序是 [Kenneth Reitz](https://github.com/kennethreitz) 编写的 [HTTPBin](https://httpbin.org/) 的 Golang 实现。\n\n[HTTPBin](https://httpbin.org/) 是一个 `HTTP Request & Response Service`，通过 Response 返回 Request 的信息，也可以根据请求指定的参数来返回需要的 HTTP Response，以便 HTTP 客户端可以方便地看到发送请求的信息，也可以用于模拟特定的服务端返回，以便做针对性的处理。\n\n\n\n### 使用方法\n\n| 参数 | 说明                     |\n| :--: | ------------------------ |\n| `-h` | 在控制台显示基础帮助信息 |\n| `-p` | 指定监听端口             |\n","mockRule":{"rules":[],"enableSystemRule":true}},"apiCollection":[{"name":"根目录","auth":{},"parentId":0,"serverId":"","description":"根目录 root 的备注","identityPattern":{"httpApi":{"type":"methodAndPath","bodyType":""}},"preProcessors":[{"id":"inheritProcessors","type":"inheritProcessors","data":{}}],"postProcessors":[{"id":"inheritProcessors","type":"inheritProcessors","data":{}}],"inheritPostProcessors":{},"inheritPreProcessors":{},"items":[{"name":"操作 Cookie","auth":{},"parentId":0,"serverId":"","description":"Hahaha","identityPattern":{"httpApi":{"type":"inherit","bodyType":""}},"preProcessors":[{"id":"inheritProcessors","type":"inheritProcessors","data":{}}],"postProcessors":[{"id":"inheritProcessors","type":"inheritProcessors","data":{}}],"inheritPostProcessors":{},"inheritPreProcessors":{},"items":[{"name":"显示客户端 Cookie","api":{"id":"132059657","method":"get","path":"/cookies","parameters":{},"auth":{},"commonParameters":{"query":[],"body":[],"cookie":[],"header":[]},"responses":[{"id":"367051411","name":"成功","code":200,"contentType":"json","jsonSchema":{"type":"object","properties":{"cookies":{"type":"array","items":{"type":"object","properties":{"Name":{"type":"string"},"Value":{"type":"string"},"Path":{"type":"string"},"Domain":{"type":"string"},"Expires":{"type":"string"},"RawExpires":{"type":"string"},"MaxAge":{"type":"integer"},"Secure":{"type":"boolean"},"HttpOnly":{"type":"boolean"},"SameSite":{"type":"integer"},"Raw":{"type":"string"}},"required":["Name","Value","Path","Domain","Expires","RawExpires","MaxAge","Secure","HttpOnly","SameSite","Raw"],"x-apifox-orders":["Name","Value","Path","Domain","Expires","RawExpires","MaxAge","Secure","HttpOnly","SameSite","Raw"]}}},"required":["cookies"],"x-apifox-orders":["cookies"]}}],"responseExamples":[{"name":"成功示例","data":"{\n    \"cookies\": [\n        {\n            \"Name\": \"key1\",\n            \"Value\": \"value1\",\n            \"Path\": \"\",\n            \"Domain\": \"\",\n            \"Expires\": \"0001-01-01T00:00:00Z\",\n            \"RawExpires\": \"\",\n            \"MaxAge\": 0,\n            \"Secure\": false,\n            \"HttpOnly\": false,\n            \"SameSite\": 0,\n            \"Raw\": \"\"\n        },\n        {\n            \"Name\": \"key2\",\n            \"Value\": \"value2\",\n            \"Path\": \"\",\n            \"Domain\": \"\",\n            \"Expires\": \"0001-01-01T00:00:00Z\",\n            \"RawExpires\": \"\",\n            \"MaxAge\": 0,\n            \"Secure\": false,\n            \"HttpOnly\": false,\n            \"SameSite\": 0,\n            \"Raw\": \"\"\n        }\n    ]\n}","responseId":367051411,"ordering":1}],"requestBody":{"type":"none","parameters":[]},"description":"显示客户端请求携带的 Cookie 信息。\n\n\n- cURL 示例\n```bash\ncurl -iL -c \"cookie.txt\" \\\n  \"http://${base_url}/cookies\"\n```\n\n- HTTP 示例\n```http\nGET {{base_url}}/cookies\n```","tags":[],"status":"developing","serverId":"","operationId":"","sourceUrl":"","ordering":10,"cases":[],"mocks":[],"customApiFields":"{}","advancedSettings":{},"mockScript":{},"codeSamples":[],"commonResponseStatus":{},"responseChildren":["BLANK.367051411"],"preProcessors":[],"postProcessors":[],"inheritPostProcessors":{},"inheritPreProcessors":{}}},{"name":"为客户端设置 Cookie","api":{"id":"132060409","method":"get","path":"/cookies/set","parameters":{"query":[{"required":false,"description":"","type":"string","id":"QFpEKkVsKd","enable":true,"name":"key1","example":"value1"},{"required":false,"description":"","type":"string","id":"o3IwO8dQ12","enable":true,"name":"key2","example":"value2"}]},"auth":{},"commonParameters":{"query":[],"body":[],"cookie":[],"header":[]},"responses":[{"id":"367051714","name":"成功","code":302,"contentType":"raw","jsonSchema":{"type":"object","properties":{}}}],"responseExamples":[{"name":"成功示例","data":"HTTP/1.1 302 Found\nAccess-Control-Allow-Credentials: true\nAccess-Control-Allow-Origin: *\nLocation: /cookies\nSet-Cookie: key1=value1; Path=/\nSet-Cookie: key2=value2; Path=/\nDate: Sun, 10 Dec 2023 05:22:12 GMT\nContent-Length: 0","responseId":367051714,"ordering":1}],"requestBody":{"type":"none","parameters":[]},"description":"通过 Params 参数指定要在 Response 中返回的 Cookie。\n\n其中每个**键值对**表示一个 Cookie 设置。\n\n服务器返回 Status Code 为 302 的 Response，通过 Set-Cookie 头来为客户端设定 Cookie，同时引导 HTTP Client 访问 /cookies 查看本地 Cookie。\n\n\n- cURL 示例\n```bash\ncurl -iL -c \"cookie.txt\" \\\n  \"http://${base_url}/cookies/set?key1=value1&key2=value2\"\n```\n\n- HTTP 示例\n```http\nGET {{base_url}}/cookies/set?key1=value1&key2=value2\n```\n","tags":[],"status":"developing","serverId":"","operationId":"","sourceUrl":"","ordering":20,"cases":[],"mocks":[],"customApiFields":"{}","advancedSettings":{},"mockScript":{},"codeSamples":[],"commonResponseStatus":{},"responseChildren":["BLANK.367051714"],"preProcessors":[],"postProcessors":[],"inheritPostProcessors":{},"inheritPreProcessors":{}}},{"name":"设置 Cookie 的详细信息","api":{"id":"132060939","method":"get","path":"/cookies/set-detail/{key}/{value}","parameters":{"query":[{"required":false,"description":"指定 Cookie 的安全性，值为 1 时，Cookie 只有在使用 HTTPS 的时候才能携带到服务端。","type":"integer","id":"llHC726MxP","enable":true,"name":"secure","example":"0,1"},{"required":false,"description":"指定 Cookie 必须由 HTTP 的 Response 指定，无法通过脚本等手段设置。","type":"integer","id":"U63xZGvKxM","enable":true,"name":"httponly","example":"0,1"}],"path":[{"id":"key#0","name":"key","required":true,"description":"指定要设置的 Cookie 的 Key。","type":"string","enable":true,"example":"key1"},{"id":"value#0","name":"value","required":true,"description":"指定要设置的 Cookie 的 Value。","type":"string","enable":true,"example":"value1"}]},"auth":{},"commonParameters":{"query":[],"body":[],"cookie":[],"header":[]},"responses":[{"id":"367052054","name":"成功","code":302,"contentType":"raw","jsonSchema":{"type":"object","properties":{}}}],"responseExamples":[{"name":"成功示例","data":"HTTP/1.1 302 Found\nAccess-Control-Allow-Credentials: true\nAccess-Control-Allow-Origin: *\nLocation: /cookies\nSet-Cookie: key1=value1; Path=/; HttpOnly; Secure\nDate: Sun, 10 Dec 2023 05:28:36 GMT\nContent-Length: 0","responseId":367052054,"ordering":1}],"requestBody":{"type":"none","parameters":[]},"description":"通过 Params 参数指定要在 Response 中返回的 Cookie。\n\n通过 `path` 中的 `key` 和 `value` 指定创建 Cookie 的 `key` 和 `value`，其它参数通过 Query Params 传递。\n\n服务器返回 Status Code 为 302 的 Response，通过 Set-Cookie 头来为客户端设定 Cookie，同时引导 HTTP Client 访问 /cookies 查看本地 Cookie。\n\n\n- cURL 示例\n```bash\ncurl -iL -c \"cookie.txt\" \\\n  \"http://${base_url}/cookies/set-detail/key/value?secure=1&httponly=1\"\n```\n\n- HTTP 示例\n```http\nGET {{base_url}}/cookies/set-detail/key/value?secure=1&httponly=1\n```\n","tags":[],"status":"developing","serverId":"","operationId":"","sourceUrl":"","ordering":30,"cases":[],"mocks":[],"customApiFields":"{}","advancedSettings":{},"mockScript":{},"codeSamples":[],"commonResponseStatus":{},"responseChildren":["BLANK.367052054"],"preProcessors":[],"postProcessors":[],"inheritPostProcessors":{},"inheritPreProcessors":{}}},{"name":"删除客户端 Cookie","api":{"id":"132070732","method":"get","path":"/cookies/delete","parameters":{"query":[{"required":false,"description":"","type":"string","id":"48XDOQwu2C","enable":true,"name":"key1","example":""},{"required":false,"description":"","type":"string","id":"NbFymMiUJt","enable":true,"name":"key2"}]},"auth":{},"commonParameters":{"query":[],"body":[],"cookie":[],"header":[]},"responses":[{"id":"367066509","name":"成功","code":302,"contentType":"raw","jsonSchema":{"type":"object","properties":{}}}],"responseExamples":[{"name":"成功示例","data":"HTTP/1.1 302 Found\nAccess-Control-Allow-Credentials: true\nAccess-Control-Allow-Origin: *\nLocation: /cookies\nSet-Cookie: key2=; Path=/; Expires=Thu, 01 Jan 1970 00:00:00 GMT\nSet-Cookie: key1=; Path=/; Expires=Thu, 01 Jan 1970 00:00:00 GMT\nDate: Sun, 10 Dec 2023 05:35:26 GMT\nContent-Length: 0","responseId":367066509,"ordering":1}],"requestBody":{"type":"none","parameters":[]},"description":"通过 Params 参数指定要在 Response 中进行清理的 Cookie。\n\n其中每个**键值对**中的 Key 表示一个要清理的 Cookie。\n\n\n\n\n- cURL 示例\n```bash\ncurl -iL  \"http://${base_url}/cookies/delete?key1&key2\"\n```\n\n- HTTP 示例\n```http\nGET {{base_url}}/cookies/delete?key1&key2\n```\n","tags":[],"status":"developing","serverId":"","operationId":"","sourceUrl":"","ordering":40,"cases":[],"mocks":[],"customApiFields":"{}","advancedSettings":{},"mockScript":{},"codeSamples":[],"commonResponseStatus":{},"responseChildren":["BLANK.367066509"],"preProcessors":[],"postProcessors":[],"inheritPostProcessors":{},"inheritPreProcessors":{}}}]},{"name":"Anything","auth":{},"parentId":0,"serverId":"","description":"","identityPattern":{"httpApi":{"type":"inherit","bodyType":""}},"preProcessors":[{"id":"inheritProcessors","type":"inheritProcessors","data":{}}],"postProcessors":[{"id":"inheritProcessors","type":"inheritProcessors","data":{}}],"inheritPostProcessors":{},"inheritPreProcessors":{},"items":[{"name":"获取请求的所有信息","api":{"id":"126134419","method":"get","path":"/anything","parameters":{},"auth":{},"commonParameters":{"query":[],"body":[],"cookie":[],"header":[]},"responses":[{"id":"354464918","name":"成功","code":200,"contentType":"json","jsonSchema":{"type":"object","properties":{"args":{"type":"object","properties":{},"x-apifox-orders":[]},"data":{"type":"string"},"files":{"type":"object","properties":{},"x-apifox-orders":[]},"form":{"type":"object","properties":{},"x-apifox-orders":[]},"headers":{"type":"object","properties":{"Accept":{"type":"string"},"Host":{"type":"string"},"User-Agent":{"type":"string"}},"x-apifox-orders":["Accept","Host","User-Agent"]},"json":{"type":"null"},"method":{"type":"string"},"url":{"type":"string"},"server_endpoints":{"type":"array","items":{"type":"string"}},"client":{"type":"string"}},"required":["args","files","form","headers","json","method","url","server_endpoints","client","data"],"x-apifox-orders":["args","data","files","form","headers","json","method","url","server_endpoints","client"]}}],"responseExamples":[{"name":"成功示例","data":"{\n    \"args\": {},\n    \"data\": \"\",\n    \"files\": {},\n    \"form\": {},\n    \"headers\": {\n        \"Accept\": \"*/*\",\n        \"Host\": \"localhost:8080\",\n        \"User-Agent\": \"curl/8.1.2\"\n    },\n    \"json\": null,\n    \"method\": \"GET\",\n    \"url\": \"/anything\",\n    \"server_endpoints\": [\n        \"192.168.50.100:8080\",\n        \"192.168.1.200:8080\",\n        \"192.168.1.7:8080\",\n        \"192.168.101.1:8080\"\n    ],\n    \"client\": \"127.0.0.1:54146\"\n}","responseId":354464918,"ordering":1}],"requestBody":{"type":"none","parameters":[]},"description":"获取请求的详细信息。\n\n\n\n- cURL 示例\n```bash\ncurl -i \"http://${base_url}/anything\"\n```\n\n- HTTP 示例\n```http\nGET {{base_url}}/anything\n```\n","tags":[],"status":"developing","serverId":"","operationId":"","sourceUrl":"","ordering":10,"cases":[],"mocks":[],"customApiFields":"{}","advancedSettings":{},"mockScript":{},"codeSamples":[],"commonResponseStatus":{},"responseChildren":["BLANK.354464918"],"preProcessors":[],"postProcessors":[],"inheritPostProcessors":{},"inheritPreProcessors":{}}}]},{"name":"重定向","auth":{},"parentId":0,"serverId":"","description":"","identityPattern":{"httpApi":{"type":"inherit","bodyType":"","fields":[]}},"preProcessors":[{"id":"inheritProcessors","type":"inheritProcessors","data":{}}],"postProcessors":[{"id":"inheritProcessors","type":"inheritProcessors","data":{}}],"inheritPostProcessors":{},"inheritPreProcessors":{},"items":[{"name":"重定向","api":{"id":"132079039","method":"get","path":"/redirect-to","parameters":{"query":[{"required":false,"description":"跳转到的 URL。","type":"string","id":"Y7MyqXeEoI","enable":true,"name":"url","example":"http://baidu.com"},{"required":false,"description":"状态码。","type":"integer","id":"WTjfDDGVrJ","enable":true,"name":"status_code","example":"302"}]},"auth":{},"commonParameters":{"query":[],"body":[],"cookie":[],"header":[]},"responses":[{"id":"367077255","name":"成功","code":302,"contentType":"raw","jsonSchema":{"type":"object","properties":{}}}],"responseExamples":[],"requestBody":{"type":"none","parameters":[]},"description":"指定服务端模拟 30X Redirect。\n\n- cURL 示例\n```bash\ncurl -iL \"${base_url}/redirect-to?url=${base_url}/anything&status_code=302\"\n```\n\n- HTTP 示例\n```http\nGET {{base_url}}/redirect-to?url={{base_url}}/anything&status_code=302\n```","tags":[],"status":"developing","serverId":"","operationId":"","sourceUrl":"","ordering":10,"cases":[],"mocks":[],"customApiFields":"{}","advancedSettings":{},"mockScript":{},"codeSamples":[],"commonResponseStatus":{},"responseChildren":["BLANK.367077255"],"preProcessors":[],"postProcessors":[],"inheritPostProcessors":{},"inheritPreProcessors":{}}}]},{"name":"认证","auth":{},"parentId":0,"serverId":"","description":"","identityPattern":{"httpApi":{"type":"inherit","bodyType":"","fields":[]}},"preProcessors":[{"id":"inheritProcessors","type":"inheritProcessors","data":{}}],"postProcessors":[{"id":"inheritProcessors","type":"inheritProcessors","data":{}}],"inheritPostProcessors":{},"inheritPreProcessors":{},"items":[{"name":"Basic Auth","api":{"id":"132080449","method":"get","path":"/basic-auth/{user}/{passwd}","parameters":{"path":[{"id":"user#0","name":"user","required":true,"description":"用户名","type":"string","enable":true,"example":"my_user_name"},{"id":"passwd#0","name":"passwd","required":true,"description":"密码","type":"string","enable":true,"example":"my_password"}]},"auth":{},"commonParameters":{"query":[],"body":[],"cookie":[],"header":[]},"responses":[{"id":"367079194","name":"成功","code":200,"contentType":"json","jsonSchema":{"type":"object","properties":{"authenticated":{"type":"boolean"},"user":{"type":"string"}},"required":["authenticated","user"],"x-apifox-orders":["authenticated","user"]}},{"id":"367079700","name":"没有权限","code":401,"contentType":"raw","jsonSchema":{"type":"object","properties":{}}}],"responseExamples":[{"name":"成功示例","data":"{\n  \"authenticated\": true,\n  \"user\": \"my_user_name\"\n}","responseId":367079194,"ordering":1},{"name":"异常示例","data":"HTTP/1.1 401 Unauthorized\nAccess-Control-Allow-Credentials: true\nAccess-Control-Allow-Origin: *\nWww-Authenticate: Basic realm=\"Fake Realm\"\nDate: Sun, 10 Dec 2023 07:45:35 GMT\nContent-Length: 0","responseId":367079700,"ordering":1}],"requestBody":{"type":"none","parameters":[]},"description":"[Basic Auth](https://developer.mozilla.org/zh-CN/docs/Web/HTTP/Authentication) 测试。\n\n通过 Path 中的 `username` 和 `password` 参数指定服务端按这两个参数进行权限校验。如果没有校验通过，则返回 401.\n\n对于浏览器访问的场景，会弹出输入用户名和密码的输入框。\n\n\n\n- cURL 示例\n\n```bash\ncurl \"${base_url}/basic-auth/my-username/my-password\" -i -u 'my-username:my-password'\n```\n\n\n\n- HTTP 示例\n\n```http\nGET {{base_url}}/basic-auth/my-username/my-password\n```\n\n\n\n","tags":[],"status":"developing","serverId":"","operationId":"","sourceUrl":"","ordering":10,"cases":[],"mocks":[],"customApiFields":"{}","advancedSettings":{},"mockScript":{},"codeSamples":[],"commonResponseStatus":{},"responseChildren":["BLANK.367079194","BLANK.367079700"],"preProcessors":[],"postProcessors":[],"inheritPostProcessors":{},"inheritPreProcessors":{}}}]},{"name":"动态数据","auth":{},"parentId":0,"serverId":"","description":"","identityPattern":{"httpApi":{"type":"inherit","bodyType":"","fields":[]}},"preProcessors":[{"id":"inheritProcessors","type":"inheritProcessors","data":{}}],"postProcessors":[{"id":"inheritProcessors","type":"inheritProcessors","data":{}}],"inheritPostProcessors":{},"inheritPreProcessors":{},"items":[{"name":"设置延时","api":{"id":"132082161","method":"get","path":"/delay/{delay}","parameters":{"path":[{"id":"delay#0","name":"delay","required":true,"description":"指定延时时间（秒）。","type":"integer","enable":true,"example":"5"}]},"auth":{},"commonParameters":{"query":[],"body":[],"cookie":[],"header":[]},"responses":[{"id":"36732793","name":"成功","code":200,"contentType":"json","jsonSchema":{"type":"object","properties":{}}}],"responseExamples":[],"requestBody":{"type":"none","parameters":[]},"description":"让服务器在等待指定时间后返回，如不指定，默认值为 3 秒，最大值为 10 秒。等待时间范围：(0, 10]\n\n\n\n- cURL 示例\n\n```bash\ncurl \"${base_url}/delay/5\"\n```\n\n​    \n\n- HTTP 示例\n\n```http\nGET {{base_url}}/delay/5\n```\n\n","tags":[],"status":"developing","serverId":"","operationId":"","sourceUrl":"","ordering":10,"cases":[],"mocks":[],"customApiFields":"{}","advancedSettings":{},"mockScript":{},"codeSamples":[],"commonResponseStatus":{},"responseChildren":["BLANK.36732793"],"preProcessors":[],"postProcessors":[],"inheritPostProcessors":{},"inheritPreProcessors":{}}},{"name":"Base64 解码（Body 传参）","api":{"id":"132083089","method":"post","path":"/base64","parameters":{"path":[]},"auth":{},"commonParameters":{"query":[],"body":[],"cookie":[],"header":[]},"responses":[{"id":"367084800","name":"成功","code":200,"contentType":"raw","jsonSchema":{"type":"object","properties":{}}}],"responseExamples":[{"name":"成功示例","data":"HTTPBIN_GO is awesome","responseId":367084800,"ordering":1}],"requestBody":{"type":"application/x-www-form-urlencoded","parameters":[{"required":false,"description":"Base64 编码的数据","type":"string","id":"lRQKoCHHuL","example":"SFRUUEJJTl9HTyBpcyBhd2Vzb21l","enable":true,"name":"base64"}]},"description":"Base64 解码，对 Body 中传递的 Base64 数据进行解码。\n\n\n\n\n- cURL 示例\n\n```bash\ncurl --data-urlencode 'base64=SFRUUEJJTl9HTyBpcyBhd2Vzb21l' \\\n    \"${base_url}/base64\"\n```\n\n​    \n\n- HTTP 示例\n\n```http\nPOST {{base_url}}/base64\nContent-Type: application/x-www-form-urlencoded\n\nbase64=SFRUUEJJTl9HTyBpcyBhd2Vzb21l\n```\n\n","tags":[],"status":"developing","serverId":"","operationId":"","sourceUrl":"","ordering":20,"cases":[],"mocks":[],"customApiFields":"{}","advancedSettings":{},"mockScript":{},"codeSamples":[],"commonResponseStatus":{},"responseChildren":["BLANK.367084800"],"preProcessors":[],"postProcessors":[],"inheritPostProcessors":{},"inheritPreProcessors":{}}},{"name":"Base64 解码（Path 传参）","api":{"id":"132083092","method":"get","path":"/base64/{base64-value}","parameters":{"path":[{"id":"base64-value#0","name":"base64-value","required":true,"description":"","type":"string","enable":true}]},"auth":{},"commonParameters":{"query":[],"body":[],"cookie":[],"header":[]},"responses":[{"id":"367082657","name":"成功","code":200,"contentType":"raw","jsonSchema":{"type":"object","properties":{}}}],"responseExamples":[{"name":"成功示例","data":"HTTPBIN_GO is awesome","responseId":367082657,"ordering":1}],"requestBody":{"type":"none","parameters":[]},"description":"Base64 解码，对 Path 中传递的 Base64 数据进行解码。\n\n\n\n\n- cURL 示例\n\n```bash\ncurl \"${base_url}/base64/SFRUUEJJTl9HTyBpcyBhd2Vzb21l\"\n```\n\n​    \n\n- HTTP 示例\n\n```http\nGET {{base_url}}/base64/SFRUUEJJTl9HTyBpcyBhd2Vzb21l\n```\n\n","tags":[],"status":"developing","serverId":"","operationId":"","sourceUrl":"","ordering":30,"cases":[],"mocks":[],"customApiFields":"{}","advancedSettings":{},"mockScript":{},"codeSamples":[],"commonResponseStatus":{},"responseChildren":["BLANK.367082657"],"preProcessors":[],"postProcessors":[],"inheritPostProcessors":{},"inheritPreProcessors":{}}},{"name":"模拟获取数据（GET 传参）","api":{"id":"132083898","method":"get","path":"/data","parameters":{"query":[{"id":"RPuglFh0CW","name":"content","example":"abcxyz123","required":true,"description":"需要通过 Response 返回的内容。","enable":true,"type":"string"},{"id":"0UynE7vyTr","name":"content-type","example":"application/octet-stream","required":false,"description":"指定通过 Response 返回内容的 Content-Type。\n如不指定，默认值为 application/octet-stream。\n如指定为 auto，则自动检测数据测 Content-Type。","enable":true,"type":"string"},{"id":"2Lt7smBvWn","name":"filename","example":"我的文件.txt","required":false,"description":"指定通过 Response 返回的内容的文件名。","enable":true,"type":"string"}],"path":[]},"auth":{},"commonParameters":{"query":[],"body":[],"cookie":[],"header":[]},"responses":[{"id":"36733870","name":"成功","code":200,"contentType":"json","jsonSchema":{"type":"object","properties":{}}}],"responseExamples":[],"requestBody":{"type":"none","parameters":[]},"description":"根据指定参数，模拟返回内容。","tags":[],"status":"developing","serverId":"","operationId":"","sourceUrl":"","ordering":40,"cases":[],"mocks":[],"customApiFields":"{}","advancedSettings":{},"mockScript":{},"codeSamples":[],"commonResponseStatus":{},"responseChildren":["BLANK.36733870"],"preProcessors":[],"postProcessors":[],"inheritPostProcessors":{},"inheritPreProcessors":{}}},{"name":"指定 Response Header（GET 传参）","api":{"id":"132116768","method":"get","path":"/response-headers","parameters":{"query":[{"id":"WdeRrpgAPq","name":"key1","example":"value1","required":false,"description":"","enable":true,"type":"string"},{"id":"fZFNDGBZFd","name":"key2","example":"value2","required":false,"description":"","enable":true,"type":"string"}]},"auth":{},"commonParameters":{"query":[],"body":[],"cookie":[],"header":[]},"responses":[{"id":"367136935","name":"成功","code":200,"contentType":"raw","jsonSchema":{"type":"object","properties":{}}}],"responseExamples":[{"name":"成功示例","data":"HTTP/1.1 200 OK\nAccess-Control-Allow-Credentials: true\nAccess-Control-Allow-Origin: *\nContent-Type: application/json\nKey1: value1\nKey2: value2\nDate: Sun, 10 Dec 2023 15:25:31 GMT\nContent-Length: 46\n\n{\n    \"key1\": \"value1\",\n    \"key2\": \"value2\"\n}","responseId":367136935,"ordering":1}],"requestBody":{"type":"none","parameters":[]},"description":"指定需要在 Response 中返回的 Header。\n\n\n\n\n- cURL 示例\n\n```bash\ncurl -i \"${base_url}/response-headers?key1=value1&key2=value2\"\n```\n\n​    \n\n- HTTP 示例\n\n```http\nGET {{base_url}}/response-headers?key1=value1&key2=value2\n```\n\n","tags":[],"status":"developing","serverId":"","operationId":"","sourceUrl":"","ordering":50,"cases":[],"mocks":[],"customApiFields":"{}","advancedSettings":{},"mockScript":{},"codeSamples":[],"commonResponseStatus":{},"responseChildren":["BLANK.367136935"],"preProcessors":[],"postProcessors":[],"inheritPostProcessors":{},"inheritPreProcessors":{}}},{"name":"指定 Response Header（POST 传参）","api":{"id":"132116886","method":"post","path":"/response-headers","parameters":{"query":[]},"auth":{},"commonParameters":{"query":[],"body":[],"cookie":[],"header":[]},"responses":[{"id":"367136849","name":"成功","code":200,"contentType":"raw","jsonSchema":{"type":"object","properties":{}}}],"responseExamples":[{"name":"成功示例","data":"HTTP/1.1 200 OK\nAccess-Control-Allow-Credentials: true\nAccess-Control-Allow-Origin: *\nContent-Type: application/json\nKey1: value1\nKey2: value2\nDate: Sun, 10 Dec 2023 15:25:31 GMT\nContent-Length: 46\n\n{\n    \"key1\": \"value1\",\n    \"key2\": \"value2\"\n}","responseId":367136849,"ordering":1}],"requestBody":{"type":"application/x-www-form-urlencoded","parameters":[{"required":false,"description":"","type":"string","id":"jPbYiTIX4Z","example":"value1","enable":true,"name":"key1"},{"required":false,"description":"","type":"string","id":"1n4lk2usUP","example":"value2","enable":true,"name":"key2"}]},"description":"指定需要在 Response 中返回的 Header。\n\n\n\n\n- cURL 示例\n\n```bash\ncurl -i \"${base_url}/response-headers\" \\\n     --data-urlencode 'key1=value1' \\\n     --data-urlencode 'key2=value2'\n```\n\n​    \n\n- HTTP 示例\n\n```http\nPOST {{base_url}}/response-headers\nContent-Type: application/x-www-form-urlencoded\n\nkey1=value1&key2=value2\n```\n\n","tags":[],"status":"developing","serverId":"","operationId":"","sourceUrl":"","ordering":56,"cases":[],"mocks":[],"customApiFields":"{}","advancedSettings":{},"mockScript":{},"codeSamples":[],"commonResponseStatus":{},"responseChildren":["BLANK.367136849"],"preProcessors":[],"postProcessors":[],"inheritPostProcessors":{},"inheritPreProcessors":{}}}]},{"name":"状态码","auth":{},"parentId":0,"serverId":"","description":"","identityPattern":{"httpApi":{"type":"inherit","bodyType":"","fields":[]}},"preProcessors":[{"id":"inheritProcessors","type":"inheritProcessors","data":{}}],"postProcessors":[{"id":"inheritProcessors","type":"inheritProcessors","data":{}}],"inheritPostProcessors":{},"inheritPreProcessors":{},"items":[{"name":"指定返回状态码","api":{"id":"132111635","method":"get","path":"/status/{code}","parameters":{"path":[{"id":"code#0","name":"code","required":true,"description":"指定要返回的状态码","type":"integer","enable":true,"example":"302"}]},"auth":{},"commonParameters":{"query":[],"body":[],"cookie":[],"header":[]},"responses":[{"id":"36743170","name":"成功","code":200,"contentType":"raw","jsonSchema":{"type":"object","properties":{}}}],"responseExamples":[],"requestBody":{"type":"none","parameters":[]},"description":"返回指定的 Status Code 及描述。\n\n如果状态码介于 `[300, 400)` 则将 Response 的 `Location` 头指定为 `/anything`\n\n\n\n\n- cURL 示例\n\n```bash\ncurl -iL \"${base_url}/status/302\"\n```\n\n​    \n\n- HTTP 示例\n\n```http\nGET {{base_url}}/status/302\n```\n\n","tags":[],"status":"developing","serverId":"","operationId":"","sourceUrl":"","ordering":10,"cases":[],"mocks":[],"customApiFields":"{}","advancedSettings":{},"mockScript":{},"codeSamples":[],"commonResponseStatus":{},"responseChildren":["BLANK.36743170"],"preProcessors":[],"postProcessors":[],"inheritPostProcessors":{},"inheritPreProcessors":{}}}]},{"name":"数据探测","auth":{},"parentId":0,"serverId":"","description":"","identityPattern":{"httpApi":{"type":"inherit","bodyType":"","fields":[]}},"preProcessors":[{"id":"inheritProcessors","type":"inheritProcessors","data":{}}],"postProcessors":[{"id":"inheritProcessors","type":"inheritProcessors","data":{}}],"inheritPostProcessors":{},"inheritPreProcessors":{},"items":[{"name":"探测数据（multipart/form-data 形式）","api":{"id":"132112463","method":"post","path":"/detect/multipart","parameters":{},"auth":{},"commonParameters":{"query":[],"body":[],"cookie":[],"header":[]},"responses":[{"id":"36743602","name":"成功","code":200,"contentType":"json","jsonSchema":{"type":"object","properties":{"size":{"type":"integer"},"Content-Type":{"type":"string"},"content":{"type":"string"}},"required":["size","Content-Type","content"],"x-apifox-orders":["size","Content-Type","content"]}}],"responseExamples":[{"name":"成功示例","data":"{\n    \"size\": 64057182,\n    \"Content-Type\": \"application/zip\",\n    \"content\": \"PK\\u0003\\u0004\\u0014\\u0000\\u0000\\u0000\\u0008\\u0000{dlQ,\\ufffdf \\ufffd\\u0000\\u0000\\u0000\\u001f\\u0001\\u0000\\u0000\\u0019\\u0000\\u001c...\"\n}","responseId":36743602,"ordering":1}],"requestBody":{"type":"multipart/form-data","parameters":[{"required":true,"description":"包含数据的文件","type":"file","id":"IVyTFpTuKt","example":"","enable":true,"name":"file"}]},"description":"检测数据类型。\n\n\n\n\n- cURL 示例\n\n```bash\ncurl \"${base_url}/detect\" -F file=@data_file\"\n```\n\n​    \n\n- HTTP 示例\n\n```http\nPOST {{base_url}}/detect\nContent-Type: multipart/form-data; boundary=----WebKitFormBoundary7MA4YWxkTrZu0gW\n\n------WebKitFormBoundary7MA4YWxkTrZu0gW\nContent-Disposition: form-data; name=\"file\"; filename=\"data_file\"\nContent-Type: application/octet-stream\n\n< data_file\n\n------WebKitFormBoundary7MA4YWxkTrZu0gW--\n```\n\n","tags":[],"status":"developing","serverId":"","operationId":"","sourceUrl":"","ordering":10,"cases":[],"mocks":[],"customApiFields":"{}","advancedSettings":{},"mockScript":{},"codeSamples":[],"commonResponseStatus":{},"responseChildren":["BLANK.36743602"],"preProcessors":[],"postProcessors":[],"inheritPostProcessors":{},"inheritPreProcessors":{}}},{"name":"探测数据（application/x-www-form-urlencoded 形式）","api":{"id":"132112526","method":"post","path":"/detect/www","parameters":{"header":[{"required":false,"description":"","type":"string","id":"JrKye44jsb","example":"{{'x-www-form-urlencoded'}}","enable":true,"name":"Content-Type"}]},"auth":{},"commonParameters":{"query":[],"body":[],"cookie":[],"header":[]},"responses":[{"id":"36743519","name":"成功","code":200,"contentType":"json","jsonSchema":{"type":"object","properties":{"size":{"type":"integer"},"Content-Type":{"type":"string"},"content":{"type":"string"}},"required":["size","Content-Type","content"],"x-apifox-orders":["size","Content-Type","content"]}}],"responseExamples":[{"name":"成功示例","data":"{\n    \"size\": 64057182,\n    \"Content-Type\": \"application/zip\",\n    \"content\": \"PK\\u0003\\u0004\\u0014\\u0000\\u0000\\u0000\\u0008\\u0000{dlQ,\\ufffdf \\ufffd\\u0000\\u0000\\u0000\\u001f\\u0001\\u0000\\u0000\\u0019\\u0000\\u001c...\"\n}","responseId":36743519,"ordering":1}],"requestBody":{"type":"application/octet-stream","parameters":[]},"description":"检测数据类型。\n\n\n\n\n- cURL 示例\n\n```bash\ncurl \"${base_url}/detect\" --data-binary @data_file\n```\n\n​    \n\n- HTTP 示例\n\n```http\nPOST {{base_url}}/detect\nContent-Type: application/x-www-form-urlencoded\n\n< data_file\n```\n\n","tags":[],"status":"developing","serverId":"","operationId":"","sourceUrl":"","ordering":16,"cases":[],"mocks":[],"customApiFields":"{}","advancedSettings":{},"mockScript":{},"codeSamples":[],"commonResponseStatus":{},"responseChildren":["BLANK.36743519"],"preProcessors":[],"postProcessors":[],"inheritPostProcessors":{},"inheritPreProcessors":{}}}]},{"name":"数据格式","auth":{},"parentId":0,"serverId":"","description":"","identityPattern":{"httpApi":{"type":"inherit","bodyType":"","fields":[]}},"preProcessors":[{"id":"inheritProcessors","type":"inheritProcessors","data":{}}],"postProcessors":[{"id":"inheritProcessors","type":"inheritProcessors","data":{}}],"inheritPostProcessors":{},"inheritPreProcessors":{},"items":[{"name":"返回 JPEG 图像","api":{"id":"132117668","method":"get","path":"/image/jpeg","parameters":{},"auth":{},"commonParameters":{"query":[],"body":[],"cookie":[],"header":[]},"responses":[{"id":"367137108","name":"成功","code":200,"contentType":"binary","jsonSchema":{"type":"object","properties":{}}}],"responseExamples":[],"requestBody":{"type":"none","parameters":[]},"description":"","tags":[],"status":"developing","serverId":"","operationId":"","sourceUrl":"","ordering":10,"cases":[],"mocks":[],"customApiFields":"{}","advancedSettings":{},"mockScript":{},"codeSamples":[],"commonResponseStatus":{},"responseChildren":["BLANK.367137108"],"preProcessors":[],"postProcessors":[],"inheritPostProcessors":{},"inheritPreProcessors":{}}},{"name":"返回 PNG 图像","api":{"id":"132117788","method":"get","path":"/image/png","parameters":{},"auth":{},"commonParameters":{"query":[],"body":[],"cookie":[],"header":[]},"responses":[{"id":"36746863","name":"成功","code":200,"contentType":"binary","jsonSchema":{"type":"object","properties":{}}}],"responseExamples":[],"requestBody":{"type":"none","parameters":[]},"description":"","tags":[],"status":"developing","serverId":"","operationId":"","sourceUrl":"","ordering":16,"cases":[],"mocks":[],"customApiFields":"{}","advancedSettings":{},"mockScript":{},"codeSamples":[],"commonResponseStatus":{},"responseChildren":["BLANK.36746863"],"preProcessors":[],"postProcessors":[],"inheritPostProcessors":{},"inheritPreProcessors":{}}},{"name":"返回 SVG 图像","api":{"id":"132117793","method":"get","path":"/image/svg","parameters":{},"auth":{},"commonParameters":{"query":[],"body":[],"cookie":[],"header":[]},"responses":[{"id":"367137614","name":"成功","code":200,"contentType":"binary","jsonSchema":{"type":"object","properties":{}}}],"responseExamples":[],"requestBody":{"type":"none","parameters":[]},"description":"","tags":[],"status":"developing","serverId":"","operationId":"","sourceUrl":"","ordering":22,"cases":[],"mocks":[],"customApiFields":"{}","advancedSettings":{},"mockScript":{},"codeSamples":[],"commonResponseStatus":{},"responseChildren":["BLANK.367137614"],"preProcessors":[],"postProcessors":[],"inheritPostProcessors":{},"inheritPreProcessors":{}}},{"name":"返回 WebP 图像","api":{"id":"132117796","method":"get","path":"/image/webp","parameters":{},"auth":{},"commonParameters":{"query":[],"body":[],"cookie":[],"header":[]},"responses":[{"id":"36746614","name":"成功","code":200,"contentType":"binary","jsonSchema":{"type":"object","properties":{}}}],"responseExamples":[],"requestBody":{"type":"none","parameters":[]},"description":"","tags":[],"status":"developing","serverId":"","operationId":"","sourceUrl":"","ordering":28,"cases":[],"mocks":[],"customApiFields":"{}","advancedSettings":{},"mockScript":{},"codeSamples":[],"commonResponseStatus":{},"responseChildren":["BLANK.36746614"],"preProcessors":[],"postProcessors":[],"inheritPostProcessors":{},"inheritPreProcessors":{}}},{"name":"返回 GIF 图像","api":{"id":"132117854","method":"get","path":"/image/gif","parameters":{},"auth":{},"commonParameters":{"query":[],"body":[],"cookie":[],"header":[]},"responses":[{"id":"36746864","name":"成功","code":200,"contentType":"binary","jsonSchema":{"type":"object","properties":{}}}],"responseExamples":[],"requestBody":{"type":"none","parameters":[]},"description":"","tags":[],"status":"developing","serverId":"","operationId":"","sourceUrl":"","ordering":34,"cases":[],"mocks":[],"customApiFields":"{}","advancedSettings":{},"mockScript":{},"codeSamples":[],"commonResponseStatus":{},"responseChildren":["BLANK.36746864"],"preProcessors":[],"postProcessors":[],"inheritPostProcessors":{},"inheritPreProcessors":{}}},{"name":"返回 JSON 数据","api":{"id":"132117970","method":"get","path":"/image/json","parameters":{},"auth":{},"commonParameters":{"query":[],"body":[],"cookie":[],"header":[]},"responses":[{"id":"367137110","name":"成功","code":200,"contentType":"json","jsonSchema":{"type":"object","properties":{}}}],"responseExamples":[],"requestBody":{"type":"none","parameters":[]},"description":"","tags":[],"status":"developing","serverId":"","operationId":"","sourceUrl":"","ordering":40,"cases":[],"mocks":[],"customApiFields":"{}","advancedSettings":{},"mockScript":{},"codeSamples":[],"commonResponseStatus":{},"responseChildren":["BLANK.367137110"],"preProcessors":[],"postProcessors":[],"inheritPostProcessors":{},"inheritPreProcessors":{}}},{"name":"返回 XML 数据","api":{"id":"132117989","method":"get","path":"/image/xml","parameters":{},"auth":{},"commonParameters":{"query":[],"body":[],"cookie":[],"header":[]},"responses":[{"id":"367137616","name":"成功","code":200,"contentType":"xml","jsonSchema":{"type":"object","properties":{}}}],"responseExamples":[],"requestBody":{"type":"none","parameters":[]},"description":"","tags":[],"status":"developing","serverId":"","operationId":"","sourceUrl":"","ordering":46,"cases":[],"mocks":[],"customApiFields":"{}","advancedSettings":{},"mockScript":{},"codeSamples":[],"commonResponseStatus":{},"responseChildren":["BLANK.367137616"],"preProcessors":[],"postProcessors":[],"inheritPostProcessors":{},"inheritPreProcessors":{}}},{"name":"返回 HTML 数据","api":{"id":"132117991","method":"get","path":"/image/html","parameters":{},"auth":{},"commonParameters":{"query":[],"body":[],"cookie":[],"header":[]},"responses":[{"id":"367137527","name":"成功","code":200,"contentType":"html","jsonSchema":{"type":"object","properties":{}}}],"responseExamples":[],"requestBody":{"type":"none","parameters":[]},"description":"","tags":[],"status":"developing","serverId":"","operationId":"","sourceUrl":"","ordering":52,"cases":[],"mocks":[],"customApiFields":"{}","advancedSettings":{},"mockScript":{},"codeSamples":[],"commonResponseStatus":{},"responseChildren":["BLANK.367137527"],"preProcessors":[],"postProcessors":[],"inheritPostProcessors":{},"inheritPreProcessors":{}}},{"name":"返回编码为 UTF-8 的内容","api":{"id":"132118050","method":"get","path":"/encoding/utf8","parameters":{},"auth":{},"commonParameters":{"query":[],"body":[],"cookie":[],"header":[]},"responses":[{"id":"367138685","name":"成功","code":200,"contentType":"html","jsonSchema":{"type":"object","properties":{}}}],"responseExamples":[],"requestBody":{"type":"none","parameters":[]},"description":"","tags":[],"status":"developing","serverId":"","operationId":"","sourceUrl":"","ordering":55,"cases":[],"mocks":[],"customApiFields":"{}","advancedSettings":{},"mockScript":{},"codeSamples":[],"commonResponseStatus":{},"responseChildren":["BLANK.367138685"],"preProcessors":[],"postProcessors":[],"inheritPostProcessors":{},"inheritPreProcessors":{}}},{"name":"返回 Gzip 数据","api":{"id":"132117995","method":"get","path":"/image/gzip","parameters":{},"auth":{},"commonParameters":{"query":[],"body":[],"cookie":[],"header":[]},"responses":[{"id":"367137115","name":"成功","code":200,"contentType":"html","jsonSchema":{"type":"object","properties":{}}}],"responseExamples":[],"requestBody":{"type":"none","parameters":[]},"description":"","tags":[],"status":"developing","serverId":"","operationId":"","sourceUrl":"","ordering":58,"cases":[],"mocks":[],"customApiFields":"{}","advancedSettings":{},"mockScript":{},"codeSamples":[],"commonResponseStatus":{},"responseChildren":["BLANK.367137115"],"preProcessors":[],"postProcessors":[],"inheritPostProcessors":{},"inheritPreProcessors":{}}}]},{"name":"Data Dump","auth":{},"parentId":0,"serverId":"","description":"","identityPattern":{"httpApi":{"type":"inherit","bodyType":"","fields":[]}},"preProcessors":[{"id":"inheritProcessors","type":"inheritProcessors","data":{}}],"postProcessors":[{"id":"inheritProcessors","type":"inheritProcessors","data":{}}],"inheritPostProcessors":{},"inheritPreProcessors":{},"items":[{"name":"显示请求的原始信息","api":{"id":"132118029","method":"get","path":"/dump/request","parameters":{},"auth":{},"commonParameters":{"query":[],"body":[],"cookie":[],"header":[]},"responses":[{"id":"36746782","name":"成功","code":200,"contentType":"html","jsonSchema":{"type":"object","properties":{}}}],"responseExamples":[],"requestBody":{"type":"none","parameters":[]},"description":"将请求的原始信息作为 Response 的 Body 返回。","tags":[],"status":"developing","serverId":"","operationId":"","sourceUrl":"","ordering":10,"cases":[],"mocks":[],"customApiFields":"{}","advancedSettings":{},"mockScript":{},"codeSamples":[],"commonResponseStatus":{},"responseChildren":["BLANK.36746782"],"preProcessors":[],"postProcessors":[],"inheritPostProcessors":{},"inheritPreProcessors":{}}}]}]}],"socketCollection":[],"docCollection":[{"name":"根目录","children":[{"name":"操作 Cookie","children":[],"items":[{"id":3377411,"name":"Cookie","content":"Cookie 相关操作zzzzzz","folderId":26017245,"type":"folder"}]},{"name":"Anything","children":[],"items":[]},{"name":"重定向","children":[],"items":[]},{"name":"认证","children":[],"items":[]},{"name":"动态数据","children":[],"items":[]},{"name":"状态码","children":[],"items":[]},{"name":"数据探测","children":[],"items":[]},{"name":"数据格式","children":[],"items":[]},{"name":"Data Dump","children":[],"items":[]}],"items":[{"id":3377410,"name":"使用说明","content":"本程序是 [Kenneth Reitz](https://github.com/kennethreitz) 编写的 [HTTPBin](https://httpbin.org/) 的 Golang 实现。\n\n[HTTPBin](https://httpbin.org/) 是一个 `HTTP Request & Response Service`，通过 Response 返回 Request 的信息，也可以根据请求指定的参数来返回需要的 HTTP Response，以便 HTTP 客户端可以方便地看到发送请求的信息，也可以用于模拟特定的服务端返回，以便做针对性的处理。\n\n\n\n### 使用方法\n\n| 参数 | 说明                     |\n| :--: | ------------------------ |\n| `-h` | 在控制台显示基础帮助信息 |\n| `-p` | 指定监听端口             |\n","folderId":0,"type":""}]}],"schemaCollection":[],"responseCollection":[{"id":3614315,"createdAt":"2023-11-19T08:20:24.000Z","updatedAt":"2023-11-19T08:20:24.000Z","deletedAt":null,"name":"根目录","type":"root","description":"","children":[],"auth":{},"projectId":3616914,"projectBranchId":0,"parentId":0,"createdById":778595,"updatedById":778595,"items":[]}],"apiTestCaseCollection":[{"name":"根目录","children":[],"items":[]}],"testCaseReferences":[],"environments":[{"name":"开发环境","parameters":{"cookie":[],"query":[],"header":[],"body":[]},"variables":[],"type":"normal","visibility":"protected","ordering":0,"tags":[{"name":"","color":"#9373EE"}],"id":"15990190","baseUrl":"http://localhost:8080","baseUrls":{"default":"http://localhost:8080"}}],"commonScripts":[],"databaseConnections":[],"globalVariables":[{"id":"3616914","variables":[{"name":"aaa","value":"","description":"","isBindInitial":false,"initialValue":""}]}],"commonParameters":null,"projectSetting":{"id":"3041284","auth":{},"servers":[{"id":"default","name":"默认服务"}],"gateway":[],"language":"zh-CN","apiStatuses":["developing","testing","released","deprecated"],"mockSettings":{},"preProcessors":[],"postProcessors":[],"advancedSettings":{},"initialDisabledMockIds":[],"cloudMock":{"security":"free","enable":false,"tokenKey":"apifoxToken"}}}